[
    {
        "name": "Piazza del Duomo",
        "description": "Main square of Florence with the Cathedral of Santa Maria del Fiore.",
        "url": "https://www.duomofirenze.it/",
        "address": "Piazza del Duomo, 50122 Firenze FI, Italia",
        "phone": "+39 055 2302885",
        "image": "/assets/img/duomo.jpg",
        "category": "historical",
        "lat": 43.773073,
        "lng": 11.256902
    },
    {
        "name": "Piazza San Marco",
        "description": "Famous square with the Basilica of San Marco in Venice.",
        "url": "https://www.basilicasanmarco.it/",
        "address": "Piazza San Marco, 30124 Venezia VE, Italia",
        "phone": "+39 041 2708311",
        "image": "/assets/img/sanmarco.jpg",
        "category": "historical",
        "lat": 45.434336,
        "lng": 12.339236
    },
    {
        "name": "Galleria Borghese",
        "description": "Art museum and sculpture gallery in Rome.",
        "url": "https://galleriaborghese.beniculturali.it/",
        "address": "Piazzale Scipione Borghese, 5, 00197 Roma RM, Italia",
        "phone": "+39 06 8413979",
        "image": "/assets/img/borghese.jpg",
        "category": "museum",
        "lat": 41.914565,
        "lng": 12.492251
    },
    {
        "name": "Torre di Pisa",
        "description": "Famous leaning tower in Piazza dei Miracoli.",
        "url": "https://www.opapisa.it/",
        "address": "Piazza del Duomo, 56126 Pisa PI, Italia",
        "phone": "+39 050 835011",
        "image": "/assets/img/pisa.jpg",
        "category": "historical",
        "lat": 43.722952,
        "lng": 10.396597
    },
    {
        "name": "Castello Sforzesco",
        "description": "Historical castle in the center of Milan.",
        "url": "https://www.milanocastello.it/",
        "address": "Piazza Castello, 20121 Milano MI, Italia",
        "phone": "+39 02 88463700",
        "image": "/assets/img/castello.jpg",
        "category": "historical",
        "lat": 45.470990,
        "lng": 9.179386
    },
    {
        "name": "Parco Sempione",
        "description": "Large park located behind the Castello Sforzesco in Milan.",
        "url": "https://www.comune.milano.it/aree-tematiche/parchi-e-giardini/parco-sempione",
        "address": "Piazza Sempione, 20154 Milano MI, Italia",
        "phone": "+39 02 02 02",
        "image": "/assets/img/parco_sempione.jpg",
        "category": "park",
        "lat": 45.480441,
        "lng": 9.168814
    },
    {
        "name": "Basilica di San Pietro",
        "description": "One of the largest and most important churches in the world, located in the Vatican.",
        "url": "https://www.vatican.va/various/basiliche/san_pietro/index_it.htm",
        "address": "Piazza San Pietro, 00120 Città del Vaticano, Italia",
        "phone": "+39 06 69883145",
        "image": "/assets/img/san_pietro.jpg",
        "category": "religious",
        "lat": 41.902783,
        "lng": 12.453900
    },
    {
        "name": "Parco della Garfagnana",
        "description": "A natural park with breathtaking landscapes in Tuscany.",
        "url": "https://www.parcogarfagnana.it/",
        "address": "Località Giuncugnano, 55030 Giuncugnano LU, Italia",
        "phone": "+39 0583 651003",
        "image": "/assets/img/garfagnana.jpg",
        "category": "park",
        "lat": 44.090982,
        "lng": 10.356762
    },
    {
        "name": "Teatro alla Scala",
        "description": "Famous opera house located in Milan.",
        "url": "https://www.teatroallascala.org/",
        "address": "Via Filodrammatici, 2, 20121 Milano MI, Italia",
        "phone": "+39 02 72003744",
        "image": "/assets/img/scala.jpg",
        "category": "modern",
        "lat": 45.465338,
        "lng": 9.189532
    },
    {
        "name": "Museo Nazionale Romano",
        "description": "Museum that collects works of art and archaeological finds in Rome.",
        "url": "https://museonazionaleromano.beniculturali.it/",
        "address": "Piazza di Villa Peretti, 1, 00185 Roma RM, Italia",
        "phone": "+39 06 39967700",
        "image": "/assets/img/museo_roman.jpg",
        "category": "museum",
        "lat": 41.902782,
        "lng": 12.496366
    },
    {
        "name": "Ponte di Rialto",
        "description": "Iconic bridge over the Grand Canal in Venice.",
        "url": "https://www.venezia.net/ponte-di-rialto.html",
        "address": "Ponte di Rialto, 30125 Venezia VE, Italia",
        "phone": "+39 041 5286200",
        "image": "/assets/img/rialto.jpg",
        "category": "modern",
        "lat": 45.437191,
        "lng": 12.335134
    },
    {
        "name": "Parco del Valentino",
        "description": "Historical park in Turin, located along the Po River.",
        "url": "https://www.turismotorino.org/it/vedere/parco-del-valentino",
        "address": "Viale Mattioli, 25, 10125 Torino TO, Italia",
        "phone": "+39 011 6660 410",
        "image": "/assets/img/valentino.jpg",
        "category": "park",
        "lat": 45.067284,
        "lng": 7.663112
    },
    {
        "name": "Cattedrale di Santa Maria del Fiore",
        "description": "Iconic cathedral in Florence with its famous dome.",
        "url": "https://www.duomofirenze.it/",
        "address": "Piazza del Duomo, 50122 Firenze FI, Italia",
        "phone": "+39 055 2302885",
        "image": "/assets/img/duomo_cupola.jpg",
        "category": "religious",
        "lat": 43.773139,
        "lng": 11.257450
    }
]